pitest.py
glamor/__init__.py
glamor/patches.py
pytest_glamor_allure/__init__.py
pytest_glamor_allure/_version.py
pytest_glamor_allure/plugin.py
pytest_glamor_allure-0.0.15.dist-info/licenses/AUTHORS.md
pytest_glamor_allure-0.0.15.dist-info/licenses/LICENSE
pytest_glamor_allure-0.0.15.dist-info/METADATA
pytest_glamor_allure-0.0.15.dist-info/WHEEL
pytest_glamor_allure-0.0.15.dist-info/entry_points.txt
pytest_glamor_allure-0.0.15.dist-info/top_level.txt
pytest_glamor_allure-0.0.15.dist-info/RECORD
