Metadata-Version: 2.4
Name: pytest_glamor_allure
Version: 0.0.15
Summary: Extends allure-pytest functionality
Home-page: https://github.com/Denis-Alexeev/pytest-glamor-allure
Author: Denis Alexeev
Author-email: github.com@alexeev.ws
Maintainer: Denis Alexeev
Maintainer-email: github.com@alexeev.ws
License: MIT
Classifier: Framework :: Pytest
Classifier: Development Status :: 5 - Production/Stable
Classifier: Intended Audience :: Developers
Classifier: License :: OSI Approved :: MIT License
Classifier: Natural Language :: Russian
Classifier: Operating System :: OS Independent
Classifier: Programming Language :: Python :: 3.8
Classifier: Programming Language :: Python :: 3.9
Classifier: Programming Language :: Python :: 3.10
Classifier: Programming Language :: Python :: 3.11
Classifier: Programming Language :: Python :: 3.12
Classifier: Programming Language :: Python :: 3.13
Classifier: Programming Language :: Python :: 3.14
Classifier: Topic :: Software Development :: Testing
Classifier: Topic :: Software Development :: Quality Assurance
Requires-Python: >=3.8
License-File: LICENSE
License-File: AUTHORS.md
Requires-Dist: allure-pytest<=2.15.3
Requires-Dist: allure-python-commons
Requires-Dist: pytest<=9.0.2
Requires-Dist: attrs<=25.4.0
Dynamic: author
Dynamic: author-email
Dynamic: classifier
Dynamic: description
Dynamic: description-content-type
Dynamic: home-page
Dynamic: license
Dynamic: license-file
Dynamic: maintainer
Dynamic: maintainer-email
Dynamic: requires-dist
Dynamic: requires-python
Dynamic: summary
